pydreamscreen/__init__.py
pydreamscreen/devices.py
pydreamscreen/network/__init__.py
pydreamscreen/network/discover.py
PyDreamScreen.HA-0.0.9.dist-info/LICENSE
PyDreamScreen.HA-0.0.9.dist-info/METADATA
PyDreamScreen.HA-0.0.9.dist-info/WHEEL
PyDreamScreen.HA-0.0.9.dist-info/top_level.txt
PyDreamScreen.HA-0.0.9.dist-info/RECORD
